{"ongoing_trials": {}, "hyperparameters": {"space": [{"class_name": "Int", "config": {"name": "n_hidden", "default": 2, "conditions": [], "min_value": 0, "max_value": 8, "step": 1, "sampling": "linear"}}, {"class_name": "Int", "config": {"name": "n_neurons", "default": null, "conditions": [], "min_value": 16, "max_value": 256, "step": 1, "sampling": "linear"}}, {"class_name": "Float", "config": {"name": "learning_rate", "default": 0.0001, "conditions": [], "min_value": 0.0001, "max_value": 0.01, "step": null, "sampling": "log"}}, {"class_name": "Choice", "config": {"name": "optimizer", "default": "sgd", "conditions": [], "values": ["sgd", "adam"], "ordered": false}}], "values": {"n_hidden": 2, "n_neurons": 16, "learning_rate": 0.0001, "optimizer": "sgd"}}, "start_order": ["0", "1", "2", "3", "4"], "end_order": ["0", "1", "2", "3", "4"], "run_times": {"0": 1, "1": 1, "2": 1, "3": 1, "4": 1}, "retry_queue": [], "seed": 123, "seed_state": 143, "tried_so_far": ["436f759b4620d7dad35b62c63706ece4", "32a15fb31a5c86f7f65b35b8a570ec18", "e73bc615d20711fdba1f0a63ee3dd3ee", "287029096b1f5e237003898ae0243474", "c6db32370688266ea7e75ad05008f522"], "id_to_hash": {"0": "287029096b1f5e237003898ae0243474", "1": "32a15fb31a5c86f7f65b35b8a570ec18", "2": "436f759b4620d7dad35b62c63706ece4", "3": "e73bc615d20711fdba1f0a63ee3dd3ee", "4": "c6db32370688266ea7e75ad05008f522"}}